{"preferredFilename":"natural_images","dataURL":"file:\/\/\/Users\/fabiofreitas\/Documents\/datasets\/natural_images\/","title":"natural_images","createdDate":"2024-02-21T20:34:13Z","dataPathRelativeToProjectURL":"..\/..\/..\/Documents\/datasets\/natural_images\/","version":"1.0","activityEntities":["dataSourceCreated",[{"createdDate":"2024-02-21T20:34:13Z","title":"Data Source Created","event":"dataSourceCreated","id":"A4B562FD-DA73-4196-869E-D90FF52983B7","subtitle":"natural_images"}],"dataSourceMetrics",[{"event":"dataSourceMetrics","title":"Data Summary","id":"726DAAF2-E31C-47D0-BCDD-28B1B1BE91B8","createdDate":"2024-02-21T20:34:43Z","subtitle":"8 Classes, 6.899 Items"},{"event":"dataSourceMetrics","subtitle":"8 Classes, 6.899 Items","createdDate":"2024-02-21T20:36:56Z","title":"Data Summary","id":"BB889F85-EF07-4447-A0A6-8AFE8C5354FD"}],"dataSourceTrainingStarted",[{"subtitle":"NaturalObjectClassifier","event":"dataSourceTrainingStarted","id":"11729534-6EA4-4562-AD4A-56F89FAA35A8","title":"Used By","createdDate":"2024-02-21T20:34:43Z"},{"createdDate":"2024-02-21T20:36:56Z","event":"dataSourceTrainingStarted","id":"F75A172E-49C4-43A4-B55B-59B56B59DF6C","title":"Used By","subtitle":"NaturalObjectClassifier copy"}]],"modifiedDate":"2024-02-21T20:39:48Z","dataResult":{"classesCount":8,"itemsCount":6899,"dataAnalysis":{"issues":[{"description":"8 classes found, including fruit, person, car","severity":"debug"},{"severity":"good","description":"6899 images found, automatically creating validation set"},{"description":"Smallest class is \"dog\" with 702 images","severity":"debug"},{"description":"Largest class is \"fruit\" with 1000 images","severity":"debug"}],"summary":{"classCount":8,"sampleCount":6899,"canUseValidation":1},"classifierAnalysis":{"labelStats":{"person":986,"flower":843,"motorbike":788,"cat":885,"airplane":727,"car":968,"fruit":1000,"dog":702}}},"createdDate":"2024-02-21T20:34:13Z","dataSourceID":"378CAEA9-5986-4EB3-8230-AC8D83EC8DD2","dataURL":"file:\/\/\/Users\/fabiofreitas\/Documents\/datasets\/natural_images\/"},"experimentIDs":["FBB4AED0-D30A-4231-B2D2-B28DAC296C0E"],"id":"378CAEA9-5986-4EB3-8230-AC8D83EC8DD2","pathType":0}