{"id":"CC52A36A-75D3-47BD-8AB2-9FF181DDE66A","preferredFilename":"Sentiment_Analisys 1","evaluationState":"uninitialized","modelEntity":{"createdDate":"2024-02-19T19:04:14Z","id":"68430565-459C-4225-AF72-BCEC63491E95","modifiedDate":"2024-02-19T19:04:14Z","title":"","version":"1.0","experimentID":"CC52A36A-75D3-47BD-8AB2-9FF181DDE66A","modelURL":"Models\/Sentiment_Analisys%201.mlmodel","preferredFilename":""},"trainingEntity":{"validationAccuracy":0.6386247256766642,"dataResult":{"dataSourceID":"E77934DE-9744-454B-BE12-1B031104794D","classesCount":3,"createdDate":"2024-02-19T19:04:14Z","itemsCount":27348,"dataURL":"file:\/\/\/Users\/fabiofreitas\/Documents\/datasets\/Tweets.csv","dataAnalysis":{"summary":{"classCount":3,"canUseValidation":1,"sampleCount":27348},"issues":[{"severity":"debug","description":"3 classes found, including neutral, positive, negative"},{"description":"27348 texts found, automatically creating validation set","severity":"good"},{"severity":"debug","description":"Smallest class is \"negative\" with 7747 texts"},{"description":"Largest class is \"neutral\" with 11056 text","severity":"debug"}],"classifierAnalysis":{"labelStats":{"positive":8545,"neutral":11056,"negative":7747}}}},"trainingAccuracy":0.924983641892152,"featureExtractionCheckpointMayBeAvailable":false,"dataSourceID":"E77934DE-9744-454B-BE12-1B031104794D","progress":[{"tableDone":false,"percentComplete":0,"currentRowIndex":0,"tableIndex":1,"count":1,"tcTrainingColumnHeader":{"elapsedTime":0,"trainingAccuracy":0.4044879078865051,"hasTraining":true,"validationAccuracy":0,"hasValidation":false,"remainingIterationCount":10},"isLast":false},{"tcTrainingColumnHeader":{"remainingIterationCount":9,"hasValidation":false,"elapsedTime":0,"validationAccuracy":0,"hasTraining":true,"trainingAccuracy":0.6167969107627869},"currentRowIndex":0,"tableDone":false,"isLast":false,"percentComplete":0,"tableIndex":1,"count":2},{"tableDone":false,"percentComplete":0,"tcTrainingColumnHeader":{"elapsedTime":0,"validationAccuracy":0,"hasTraining":true,"trainingAccuracy":0.7040144801139832,"remainingIterationCount":8,"hasValidation":false},"tableIndex":1,"count":3,"isLast":false,"currentRowIndex":0},{"count":4,"percentComplete":0,"tableDone":false,"tableIndex":1,"tcTrainingColumnHeader":{"remainingIterationCount":7,"hasValidation":false,"trainingAccuracy":0.7605172991752625,"validationAccuracy":0,"elapsedTime":0,"hasTraining":true},"currentRowIndex":0,"isLast":false},{"tcTrainingColumnHeader":{"validationAccuracy":0,"hasValidation":false,"elapsedTime":0,"trainingAccuracy":0.79538893699646,"hasTraining":true,"remainingIterationCount":6},"tableDone":false,"isLast":false,"currentRowIndex":0,"percentComplete":0,"tableIndex":1,"count":5},{"isLast":false,"percentComplete":0,"tableDone":false,"tableIndex":1,"count":6,"currentRowIndex":0,"tcTrainingColumnHeader":{"remainingIterationCount":5,"hasTraining":true,"hasValidation":false,"trainingAccuracy":0.8271428942680359,"elapsedTime":0,"validationAccuracy":0}},{"tableDone":false,"tcTrainingColumnHeader":{"remainingIterationCount":4,"elapsedTime":0,"hasTraining":true,"trainingAccuracy":0.8535853028297424,"hasValidation":false,"validationAccuracy":0},"isLast":false,"tableIndex":1,"percentComplete":0,"currentRowIndex":0,"count":7},{"currentRowIndex":0,"isLast":false,"tcTrainingColumnHeader":{"trainingAccuracy":0.8802201747894287,"hasValidation":false,"elapsedTime":0,"remainingIterationCount":3,"validationAccuracy":0,"hasTraining":true},"count":8,"percentComplete":0,"tableIndex":1,"tableDone":false},{"tableIndex":1,"tableDone":false,"count":9,"currentRowIndex":0,"percentComplete":0,"isLast":false,"tcTrainingColumnHeader":{"trainingAccuracy":0.9018128514289856,"validationAccuracy":0,"elapsedTime":0,"hasTraining":true,"hasValidation":false,"remainingIterationCount":2}},{"tableIndex":1,"percentComplete":0,"currentRowIndex":0,"count":10,"isLast":false,"tableDone":true,"tcTrainingColumnHeader":{"hasValidation":false,"elapsedTime":0,"trainingAccuracy":0.9127054214477539,"validationAccuracy":0,"hasTraining":true,"remainingIterationCount":1}},{"isLast":false,"tableIndex":0,"tableDone":false,"percentComplete":0,"count":81,"currentRowIndex":0},{"tableIndex":0,"count":181,"percentComplete":0,"currentRowIndex":0,"tableDone":false,"isLast":false},{"tableDone":false,"percentComplete":0,"currentRowIndex":0,"count":281,"tableIndex":0,"isLast":false},{"count":381,"currentRowIndex":0,"tableIndex":0,"isLast":false,"tableDone":false,"percentComplete":0},{"currentRowIndex":0,"isLast":false,"tableDone":false,"count":481,"percentComplete":0,"tableIndex":0},{"isLast":false,"percentComplete":0,"currentRowIndex":0,"tableIndex":0,"count":581,"tableDone":false},{"currentRowIndex":0,"isLast":false,"count":681,"percentComplete":0,"tableDone":false,"tableIndex":0},{"tableIndex":0,"isLast":false,"currentRowIndex":0,"percentComplete":0,"count":781,"tableDone":false},{"tableIndex":0,"percentComplete":0,"currentRowIndex":0,"tableDone":false,"isLast":false,"count":881},{"isLast":false,"tableIndex":0,"count":981,"tableDone":false,"percentComplete":0,"currentRowIndex":0},{"percentComplete":0,"count":1081,"tableIndex":0,"isLast":false,"tableDone":false,"currentRowIndex":0},{"isLast":false,"currentRowIndex":0,"count":1181,"tableIndex":0,"percentComplete":0,"tableDone":false},{"tableIndex":0,"tableDone":false,"currentRowIndex":0,"isLast":false,"count":1281,"percentComplete":0},{"count":1381,"percentComplete":0,"currentRowIndex":0,"isLast":false,"tableDone":false,"tableIndex":0},{"tableIndex":0,"currentRowIndex":0,"percentComplete":0,"count":1481,"tableDone":false,"isLast":false},{"count":1581,"percentComplete":0,"currentRowIndex":0,"tableDone":false,"tableIndex":0,"isLast":false},{"tableIndex":0,"isLast":false,"count":1681,"currentRowIndex":0,"tableDone":false,"percentComplete":0},{"tableIndex":0,"currentRowIndex":0,"count":1781,"tableDone":false,"isLast":false,"percentComplete":0},{"isLast":false,"tableIndex":0,"count":1881,"tableDone":false,"percentComplete":0,"currentRowIndex":0},{"tableDone":false,"currentRowIndex":0,"count":1981,"percentComplete":0,"isLast":false,"tableIndex":0},{"tableIndex":0,"currentRowIndex":0,"percentComplete":0,"isLast":false,"count":2081,"tableDone":false},{"percentComplete":0,"tableDone":false,"tableIndex":0,"isLast":false,"count":2181,"currentRowIndex":0},{"currentRowIndex":0,"tableDone":false,"isLast":false,"count":2281,"percentComplete":0,"tableIndex":0},{"currentRowIndex":0,"count":2381,"percentComplete":0,"tableDone":false,"tableIndex":0,"isLast":false},{"percentComplete":0,"currentRowIndex":0,"count":2481,"tableDone":false,"isLast":false,"tableIndex":0},{"tableIndex":0,"currentRowIndex":0,"percentComplete":0,"count":2581,"isLast":false,"tableDone":false},{"count":2681,"tableIndex":0,"isLast":false,"percentComplete":0,"currentRowIndex":0,"tableDone":false},{"tableIndex":0,"isLast":false,"tableDone":false,"percentComplete":0,"count":2781,"currentRowIndex":0},{"count":2881,"percentComplete":0,"tableIndex":0,"currentRowIndex":0,"isLast":false,"tableDone":false},{"isLast":false,"percentComplete":0,"currentRowIndex":0,"count":2981,"tableIndex":0,"tableDone":false},{"currentRowIndex":0,"percentComplete":0,"tableIndex":0,"isLast":false,"count":3081,"tableDone":false},{"currentRowIndex":0,"tableIndex":0,"tableDone":false,"isLast":false,"percentComplete":0,"count":3181},{"tableIndex":0,"isLast":false,"count":3281,"percentComplete":0,"tableDone":false,"currentRowIndex":0},{"tableIndex":0,"count":3381,"currentRowIndex":0,"percentComplete":0,"isLast":false,"tableDone":false},{"currentRowIndex":0,"isLast":false,"tableDone":false,"count":3481,"tableIndex":0,"percentComplete":0},{"tableIndex":0,"currentRowIndex":0,"isLast":false,"count":3581,"percentComplete":0,"tableDone":false},{"currentRowIndex":0,"count":3681,"percentComplete":0,"tableDone":false,"tableIndex":0,"isLast":false},{"currentRowIndex":0,"count":3781,"tableIndex":0,"isLast":false,"tableDone":false,"percentComplete":0},{"tableIndex":0,"isLast":false,"count":3881,"percentComplete":0,"tableDone":false,"currentRowIndex":0},{"currentRowIndex":0,"count":3981,"tableDone":false,"percentComplete":0,"isLast":false,"tableIndex":0},{"count":4081,"tableDone":false,"tableIndex":0,"currentRowIndex":0,"isLast":false,"percentComplete":0},{"tableDone":false,"percentComplete":0,"isLast":false,"count":4181,"tableIndex":0,"currentRowIndex":0},{"percentComplete":0,"isLast":false,"tableDone":false,"tableIndex":0,"currentRowIndex":0,"count":4281},{"tableDone":false,"tableIndex":0,"currentRowIndex":0,"isLast":false,"count":4381,"percentComplete":0},{"tableIndex":0,"currentRowIndex":0,"isLast":false,"tableDone":false,"count":4481,"percentComplete":0},{"tableDone":false,"currentRowIndex":0,"isLast":false,"percentComplete":0,"count":4581,"tableIndex":0},{"tableDone":false,"currentRowIndex":0,"count":4681,"isLast":false,"tableIndex":0,"percentComplete":0},{"currentRowIndex":0,"isLast":false,"percentComplete":0,"tableDone":false,"count":4781,"tableIndex":0},{"currentRowIndex":0,"tableDone":false,"isLast":false,"percentComplete":0,"count":4881,"tableIndex":0},{"currentRowIndex":0,"tableIndex":0,"count":4981,"tableDone":false,"isLast":false,"percentComplete":0},{"isLast":false,"currentRowIndex":0,"count":5081,"percentComplete":0,"tableIndex":0,"tableDone":false},{"percentComplete":0,"currentRowIndex":0,"tableIndex":0,"count":5181,"tableDone":false,"isLast":false},{"percentComplete":0,"tableIndex":0,"currentRowIndex":0,"tableDone":false,"isLast":false,"count":5281},{"tableIndex":0,"currentRowIndex":0,"percentComplete":0,"tableDone":false,"isLast":false,"count":5381},{"count":5481,"tableIndex":0,"currentRowIndex":0,"isLast":false,"percentComplete":0,"tableDone":false},{"currentRowIndex":0,"tableIndex":0,"isLast":false,"tableDone":false,"count":5581,"percentComplete":0},{"tableIndex":0,"currentRowIndex":0,"tableDone":false,"count":5681,"percentComplete":0,"isLast":false},{"count":5781,"tableIndex":0,"tableDone":false,"isLast":false,"percentComplete":0,"currentRowIndex":0},{"tableIndex":0,"count":5881,"tableDone":false,"percentComplete":0,"isLast":false,"currentRowIndex":0},{"count":5981,"isLast":false,"tableIndex":0,"currentRowIndex":0,"percentComplete":0,"tableDone":false},{"tableDone":false,"tableIndex":0,"currentRowIndex":0,"percentComplete":0,"isLast":false,"count":6081},{"currentRowIndex":0,"percentComplete":0,"tableDone":false,"isLast":false,"count":6181,"tableIndex":0},{"tableIndex":0,"tableDone":false,"isLast":false,"percentComplete":0,"currentRowIndex":0,"count":6281},{"currentRowIndex":0,"tableDone":false,"percentComplete":0,"isLast":false,"count":6381,"tableIndex":0},{"tableDone":false,"currentRowIndex":0,"count":6481,"tableIndex":0,"isLast":false,"percentComplete":0},{"count":6581,"percentComplete":0,"tableIndex":0,"isLast":false,"tableDone":false,"currentRowIndex":0},{"percentComplete":0,"isLast":false,"tableDone":false,"currentRowIndex":0,"count":6681,"tableIndex":0},{"count":6781,"percentComplete":0,"currentRowIndex":0,"tableIndex":0,"isLast":false,"tableDone":false},{"tableIndex":0,"count":6881,"currentRowIndex":0,"isLast":false,"percentComplete":0,"tableDone":false},{"tableDone":false,"isLast":false,"count":6981,"percentComplete":0,"tableIndex":0,"currentRowIndex":0},{"currentRowIndex":0,"tableIndex":0,"percentComplete":0,"isLast":false,"tableDone":false,"count":7081},{"tableIndex":0,"currentRowIndex":0,"isLast":false,"tableDone":false,"percentComplete":0,"count":7181},{"tableIndex":0,"currentRowIndex":0,"tableDone":false,"isLast":false,"count":7281,"percentComplete":0},{"tableDone":false,"tableIndex":0,"count":7381,"percentComplete":0,"currentRowIndex":0,"isLast":false},{"currentRowIndex":0,"isLast":false,"percentComplete":0,"tableIndex":0,"count":7481,"tableDone":false},{"tableDone":false,"tableIndex":0,"currentRowIndex":0,"isLast":false,"percentComplete":0,"count":7581},{"tableDone":false,"currentRowIndex":0,"isLast":false,"count":7681,"percentComplete":0,"tableIndex":0},{"tableDone":false,"currentRowIndex":0,"isLast":false,"tableIndex":0,"count":7781,"percentComplete":0},{"tableIndex":0,"count":7881,"percentComplete":0,"tableDone":false,"currentRowIndex":0,"isLast":false},{"percentComplete":0,"tableIndex":0,"count":7981,"isLast":false,"currentRowIndex":0,"tableDone":false},{"count":8081,"isLast":false,"tableIndex":0,"tableDone":false,"currentRowIndex":0,"percentComplete":0},{"count":8181,"tableIndex":0,"percentComplete":0,"tableDone":false,"isLast":false,"currentRowIndex":0},{"count":8281,"tableIndex":0,"percentComplete":0,"isLast":false,"tableDone":false,"currentRowIndex":0},{"count":8381,"percentComplete":0,"tableIndex":0,"tableDone":false,"isLast":false,"currentRowIndex":0},{"currentRowIndex":0,"isLast":false,"percentComplete":0,"tableDone":false,"count":8481,"tableIndex":0},{"tableDone":false,"tableIndex":0,"count":8581,"isLast":false,"percentComplete":0,"currentRowIndex":0},{"count":8681,"tableDone":false,"tableIndex":0,"isLast":false,"percentComplete":0,"currentRowIndex":0},{"percentComplete":0,"currentRowIndex":0,"isLast":false,"tableDone":false,"tableIndex":0,"count":8781},{"isLast":false,"tableDone":false,"currentRowIndex":0,"count":8881,"tableIndex":0,"percentComplete":0},{"count":8981,"currentRowIndex":0,"isLast":false,"percentComplete":0,"tableIndex":0,"tableDone":false},{"percentComplete":0,"tableDone":false,"currentRowIndex":0,"isLast":false,"tableIndex":0,"count":9081},{"percentComplete":0,"tableIndex":0,"tableDone":false,"currentRowIndex":0,"isLast":false,"count":9181},{"percentComplete":0,"count":9281,"tableDone":false,"tableIndex":0,"currentRowIndex":0,"isLast":false},{"tableDone":false,"count":9381,"percentComplete":0,"tableIndex":0,"currentRowIndex":0,"isLast":false},{"percentComplete":0,"currentRowIndex":0,"isLast":false,"count":9481,"tableIndex":0,"tableDone":false},{"count":9581,"currentRowIndex":0,"percentComplete":0,"tableDone":false,"isLast":false,"tableIndex":0},{"tableDone":false,"tableIndex":0,"count":9681,"isLast":false,"currentRowIndex":0,"percentComplete":0},{"count":9781,"isLast":false,"tableDone":false,"currentRowIndex":0,"percentComplete":0,"tableIndex":0},{"count":9881,"percentComplete":0,"tableIndex":0,"tableDone":false,"currentRowIndex":0,"isLast":false},{"count":9981,"tableDone":false,"currentRowIndex":0,"percentComplete":0,"isLast":false,"tableIndex":0},{"percentComplete":0,"tableIndex":0,"currentRowIndex":0,"count":10081,"isLast":false,"tableDone":false},{"count":10181,"percentComplete":0,"isLast":false,"tableDone":false,"tableIndex":0,"currentRowIndex":0},{"percentComplete":0,"count":10281,"isLast":false,"currentRowIndex":0,"tableDone":false,"tableIndex":0},{"isLast":false,"currentRowIndex":0,"count":10381,"percentComplete":0,"tableDone":false,"tableIndex":0},{"count":10481,"currentRowIndex":0,"percentComplete":0,"tableDone":false,"tableIndex":0,"isLast":false},{"isLast":false,"tableIndex":0,"count":10581,"tableDone":false,"currentRowIndex":0,"percentComplete":0},{"tableIndex":0,"count":10681,"isLast":false,"percentComplete":0,"currentRowIndex":0,"tableDone":false},{"currentRowIndex":0,"isLast":false,"tableDone":false,"tableIndex":0,"count":10781,"percentComplete":0},{"currentRowIndex":0,"tableDone":false,"isLast":false,"percentComplete":0,"count":10881,"tableIndex":0},{"isLast":false,"tableIndex":0,"tableDone":false,"currentRowIndex":0,"count":10981,"percentComplete":0},{"tableDone":false,"tableIndex":0,"isLast":false,"currentRowIndex":0,"count":11081,"percentComplete":0},{"tableDone":false,"isLast":false,"count":11181,"tableIndex":0,"currentRowIndex":0,"percentComplete":0},{"currentRowIndex":0,"percentComplete":0,"tableIndex":0,"count":11281,"isLast":false,"tableDone":false},{"percentComplete":0,"isLast":false,"tableDone":false,"tableIndex":0,"currentRowIndex":0,"count":11381},{"currentRowIndex":0,"tableIndex":0,"count":11481,"percentComplete":0,"isLast":false,"tableDone":false},{"isLast":false,"tableIndex":0,"currentRowIndex":0,"tableDone":false,"count":11581,"percentComplete":0},{"count":11681,"currentRowIndex":0,"tableDone":false,"tableIndex":0,"isLast":false,"percentComplete":0},{"percentComplete":0,"tableDone":false,"currentRowIndex":0,"tableIndex":0,"isLast":false,"count":11781},{"tableDone":false,"currentRowIndex":0,"isLast":false,"tableIndex":0,"count":11881,"percentComplete":0},{"percentComplete":0,"tableIndex":0,"tableDone":false,"count":11981,"currentRowIndex":0,"isLast":false},{"currentRowIndex":0,"tableIndex":0,"tableDone":false,"isLast":false,"count":12081,"percentComplete":0},{"tableIndex":0,"tableDone":false,"isLast":false,"count":12181,"percentComplete":0,"currentRowIndex":0},{"isLast":false,"percentComplete":0,"tableDone":false,"tableIndex":0,"currentRowIndex":0,"count":12281},{"count":12381,"tableDone":false,"percentComplete":0,"currentRowIndex":0,"tableIndex":0,"isLast":false},{"isLast":false,"currentRowIndex":0,"count":12481,"percentComplete":0,"tableIndex":0,"tableDone":false},{"tableIndex":0,"count":12581,"percentComplete":0,"currentRowIndex":0,"isLast":false,"tableDone":false},{"percentComplete":0,"isLast":false,"tableIndex":0,"count":12681,"currentRowIndex":0,"tableDone":false},{"tableIndex":0,"isLast":false,"percentComplete":0,"currentRowIndex":0,"count":12781,"tableDone":false},{"count":12881,"percentComplete":0,"tableDone":false,"isLast":false,"currentRowIndex":0,"tableIndex":0},{"tableIndex":0,"isLast":false,"currentRowIndex":0,"tableDone":false,"count":12981,"percentComplete":0},{"tableDone":false,"count":13081,"isLast":false,"percentComplete":0,"tableIndex":0,"currentRowIndex":0},{"isLast":false,"count":13181,"currentRowIndex":0,"tableIndex":0,"tableDone":false,"percentComplete":0},{"tableIndex":0,"count":13281,"percentComplete":0,"isLast":false,"currentRowIndex":0,"tableDone":false},{"currentRowIndex":0,"count":13381,"tableIndex":0,"isLast":false,"percentComplete":0,"tableDone":false},{"tableDone":false,"tableIndex":0,"isLast":false,"currentRowIndex":0,"count":13481,"percentComplete":0},{"count":13581,"percentComplete":0,"currentRowIndex":0,"tableIndex":0,"tableDone":false,"isLast":false},{"count":13681,"tableDone":false,"currentRowIndex":0,"tableIndex":0,"isLast":false,"percentComplete":0},{"tableDone":false,"isLast":false,"currentRowIndex":0,"percentComplete":0,"tableIndex":0,"count":13781},{"currentRowIndex":0,"isLast":false,"count":13881,"percentComplete":0,"tableDone":false,"tableIndex":0},{"currentRowIndex":0,"tableIndex":0,"tableDone":false,"isLast":false,"count":13981,"percentComplete":0},{"tableDone":false,"currentRowIndex":0,"percentComplete":0,"tableIndex":0,"isLast":false,"count":14081},{"currentRowIndex":0,"percentComplete":0,"tableDone":false,"count":14181,"isLast":false,"tableIndex":0},{"tableDone":false,"tableIndex":0,"currentRowIndex":0,"isLast":false,"count":14281,"percentComplete":0},{"tableDone":false,"count":14381,"currentRowIndex":0,"tableIndex":0,"isLast":false,"percentComplete":0},{"currentRowIndex":0,"tableDone":false,"isLast":false,"count":14481,"tableIndex":0,"percentComplete":0},{"percentComplete":0,"count":14581,"tableDone":false,"currentRowIndex":0,"tableIndex":0,"isLast":false},{"tableDone":false,"tableIndex":0,"isLast":false,"count":14681,"currentRowIndex":0,"percentComplete":0},{"percentComplete":0,"isLast":false,"tableDone":false,"currentRowIndex":0,"tableIndex":0,"count":14781},{"percentComplete":0,"count":14881,"currentRowIndex":0,"tableDone":false,"isLast":false,"tableIndex":0},{"currentRowIndex":0,"isLast":false,"tableIndex":0,"count":14981,"percentComplete":0,"tableDone":false},{"count":15081,"currentRowIndex":0,"isLast":false,"tableIndex":0,"percentComplete":0,"tableDone":false},{"percentComplete":0,"currentRowIndex":0,"count":15181,"tableDone":false,"tableIndex":0,"isLast":false},{"isLast":false,"percentComplete":0,"currentRowIndex":0,"tableIndex":0,"tableDone":false,"count":15281},{"isLast":false,"count":15381,"percentComplete":0,"tableIndex":0,"tableDone":false,"currentRowIndex":0},{"count":15481,"tableDone":false,"percentComplete":0,"isLast":false,"tableIndex":0,"currentRowIndex":0},{"isLast":false,"tableDone":false,"count":15581,"percentComplete":0,"currentRowIndex":0,"tableIndex":0},{"percentComplete":0,"tableDone":false,"currentRowIndex":0,"tableIndex":0,"isLast":false,"count":15681},{"tableDone":false,"tableIndex":0,"percentComplete":0,"isLast":false,"count":15781,"currentRowIndex":0},{"tableDone":false,"count":15881,"tableIndex":0,"percentComplete":0,"currentRowIndex":0,"isLast":false},{"count":15981,"percentComplete":0,"isLast":false,"tableDone":false,"currentRowIndex":0,"tableIndex":0},{"tableIndex":0,"currentRowIndex":0,"tableDone":false,"isLast":false,"count":16081,"percentComplete":0},{"isLast":false,"count":16181,"percentComplete":0,"tableIndex":0,"currentRowIndex":0,"tableDone":false},{"tableIndex":0,"tableDone":false,"currentRowIndex":0,"isLast":false,"count":16281,"percentComplete":0},{"isLast":false,"currentRowIndex":0,"count":16381,"tableDone":false,"percentComplete":0,"tableIndex":0},{"tableIndex":0,"count":16481,"currentRowIndex":0,"tableDone":false,"percentComplete":0,"isLast":false},{"isLast":false,"percentComplete":0,"tableIndex":0,"tableDone":false,"count":16581,"currentRowIndex":0},{"currentRowIndex":0,"count":16681,"percentComplete":0,"tableDone":false,"isLast":false,"tableIndex":0},{"currentRowIndex":0,"percentComplete":0,"tableIndex":0,"count":16781,"tableDone":false,"isLast":false},{"tableDone":false,"percentComplete":0,"tableIndex":0,"count":16881,"currentRowIndex":0,"isLast":false},{"tableIndex":0,"count":16981,"percentComplete":0,"tableDone":false,"currentRowIndex":0,"isLast":false},{"isLast":false,"count":17081,"percentComplete":0,"tableDone":false,"tableIndex":0,"currentRowIndex":0},{"count":17181,"percentComplete":0,"currentRowIndex":0,"tableIndex":0,"tableDone":false,"isLast":false},{"tableIndex":0,"tableDone":false,"currentRowIndex":0,"isLast":false,"percentComplete":0,"count":17281},{"count":17381,"percentComplete":0,"tableDone":false,"currentRowIndex":0,"isLast":false,"tableIndex":0},{"count":17481,"tableDone":false,"tableIndex":0,"percentComplete":0,"currentRowIndex":0,"isLast":false},{"currentRowIndex":0,"isLast":false,"tableDone":false,"tableIndex":0,"count":17581,"percentComplete":0},{"tableIndex":0,"currentRowIndex":0,"count":17681,"percentComplete":0,"tableDone":false,"isLast":false},{"tableDone":false,"tableIndex":0,"currentRowIndex":0,"isLast":false,"percentComplete":0,"count":17781},{"tableDone":false,"count":17881,"isLast":false,"percentComplete":0,"currentRowIndex":0,"tableIndex":0},{"isLast":false,"count":17981,"percentComplete":0,"currentRowIndex":0,"tableIndex":0,"tableDone":false},{"percentComplete":0,"tableDone":false,"tableIndex":0,"count":18081,"currentRowIndex":0,"isLast":false},{"tableIndex":0,"currentRowIndex":0,"isLast":false,"percentComplete":0,"tableDone":false,"count":18181},{"count":18281,"isLast":false,"percentComplete":0,"tableIndex":0,"currentRowIndex":0,"tableDone":false},{"tableDone":false,"tableIndex":0,"percentComplete":0,"count":18381,"currentRowIndex":0,"isLast":false},{"tableDone":false,"tableIndex":0,"isLast":false,"percentComplete":0,"count":18481,"currentRowIndex":0},{"isLast":false,"percentComplete":0,"tableDone":false,"count":18581,"tableIndex":0,"currentRowIndex":0},{"isLast":false,"tableIndex":0,"currentRowIndex":0,"tableDone":false,"count":18681,"percentComplete":0},{"tableDone":false,"count":18781,"percentComplete":0,"currentRowIndex":0,"isLast":false,"tableIndex":0},{"isLast":false,"percentComplete":0,"tableDone":false,"currentRowIndex":0,"count":18881,"tableIndex":0},{"currentRowIndex":0,"isLast":false,"count":18981,"percentComplete":0,"tableIndex":0,"tableDone":false},{"isLast":false,"tableDone":false,"currentRowIndex":0,"count":19081,"percentComplete":0,"tableIndex":0},{"currentRowIndex":0,"tableDone":false,"isLast":false,"tableIndex":0,"count":19181,"percentComplete":0},{"tableIndex":0,"tableDone":false,"currentRowIndex":0,"count":19281,"percentComplete":0,"isLast":false},{"currentRowIndex":0,"tableDone":false,"tableIndex":0,"isLast":false,"count":19381,"percentComplete":0},{"currentRowIndex":0,"tableIndex":0,"isLast":false,"tableDone":false,"percentComplete":0,"count":19481},{"percentComplete":0,"tableIndex":0,"currentRowIndex":0,"count":19581,"isLast":false,"tableDone":false},{"isLast":false,"tableDone":false,"currentRowIndex":0,"count":19681,"tableIndex":0,"percentComplete":0},{"currentRowIndex":0,"tableDone":false,"count":19781,"percentComplete":0,"tableIndex":0,"isLast":false},{"currentRowIndex":0,"count":19881,"percentComplete":0,"isLast":false,"tableDone":false,"tableIndex":0},{"tableIndex":0,"currentRowIndex":0,"tableDone":false,"percentComplete":0,"count":19981,"isLast":false},{"count":20081,"percentComplete":0,"tableDone":false,"tableIndex":0,"currentRowIndex":0,"isLast":false},{"percentComplete":0,"tableIndex":0,"currentRowIndex":0,"tableDone":false,"count":20181,"isLast":false},{"percentComplete":0,"tableIndex":0,"count":20281,"isLast":false,"currentRowIndex":0,"tableDone":false},{"tableIndex":0,"tableDone":false,"isLast":false,"currentRowIndex":0,"percentComplete":0,"count":20381},{"tableDone":false,"isLast":false,"percentComplete":0,"tableIndex":0,"currentRowIndex":0,"count":20481},{"isLast":false,"currentRowIndex":0,"count":20581,"tableIndex":0,"tableDone":false,"percentComplete":0},{"isLast":false,"currentRowIndex":0,"tableIndex":0,"count":20681,"percentComplete":0,"tableDone":false},{"tableDone":false,"currentRowIndex":0,"tableIndex":0,"isLast":false,"count":20781,"percentComplete":0},{"tableIndex":0,"currentRowIndex":0,"tableDone":false,"count":20881,"isLast":false,"percentComplete":0},{"tableDone":false,"currentRowIndex":0,"percentComplete":0,"isLast":false,"count":20981,"tableIndex":0},{"tableIndex":0,"currentRowIndex":0,"isLast":false,"tableDone":false,"percentComplete":0,"count":21081},{"tableIndex":0,"tableDone":false,"currentRowIndex":0,"isLast":false,"count":21181,"percentComplete":0},{"tableIndex":0,"currentRowIndex":0,"count":21281,"isLast":false,"percentComplete":0,"tableDone":false},{"isLast":false,"currentRowIndex":0,"percentComplete":0,"count":21381,"tableDone":false,"tableIndex":0},{"isLast":false,"count":21481,"currentRowIndex":0,"percentComplete":0,"tableIndex":0,"tableDone":false},{"isLast":false,"tableIndex":0,"count":21581,"percentComplete":0,"tableDone":false,"currentRowIndex":0},{"tableIndex":0,"percentComplete":0,"tableDone":false,"currentRowIndex":0,"isLast":false,"count":21681},{"tableIndex":0,"isLast":false,"count":21781,"currentRowIndex":0,"tableDone":false,"percentComplete":0},{"count":21881,"percentComplete":0,"tableDone":false,"currentRowIndex":0,"tableIndex":0,"isLast":false},{"percentComplete":0,"currentRowIndex":0,"count":21981,"isLast":false,"tableIndex":0,"tableDone":false},{"tableDone":false,"currentRowIndex":0,"count":22081,"tableIndex":0,"isLast":false,"percentComplete":0},{"tableIndex":0,"percentComplete":0,"tableDone":false,"currentRowIndex":0,"isLast":false,"count":22181},{"tableIndex":0,"tableDone":false,"currentRowIndex":0,"isLast":false,"count":22281,"percentComplete":0},{"count":22381,"tableDone":false,"tableIndex":0,"percentComplete":0,"isLast":false,"currentRowIndex":0},{"currentRowIndex":0,"isLast":false,"percentComplete":0,"count":22481,"tableDone":false,"tableIndex":0},{"tableDone":false,"tableIndex":0,"currentRowIndex":0,"isLast":false,"count":22581,"percentComplete":0},{"tableDone":false,"tableIndex":0,"isLast":false,"percentComplete":0,"count":22681,"currentRowIndex":0},{"percentComplete":0,"currentRowIndex":0,"tableDone":false,"tableIndex":0,"isLast":false,"count":22781},{"tableIndex":0,"currentRowIndex":0,"isLast":false,"count":22881,"percentComplete":0,"tableDone":false},{"currentRowIndex":0,"tableIndex":0,"tableDone":false,"percentComplete":0,"isLast":false,"count":22981},{"count":23081,"isLast":false,"currentRowIndex":0,"tableDone":false,"tableIndex":0,"percentComplete":0},{"count":23181,"isLast":false,"tableDone":false,"tableIndex":0,"percentComplete":0,"currentRowIndex":0},{"percentComplete":0,"isLast":false,"tableDone":false,"tableIndex":0,"currentRowIndex":0,"count":23281},{"currentRowIndex":0,"isLast":false,"count":23381,"percentComplete":0,"tableIndex":0,"tableDone":false},{"count":23481,"percentComplete":0,"isLast":false,"tableDone":false,"tableIndex":0,"currentRowIndex":0},{"percentComplete":0,"tableDone":false,"tableIndex":0,"currentRowIndex":0,"isLast":false,"count":23581},{"tableIndex":0,"count":23681,"isLast":false,"currentRowIndex":0,"tableDone":false,"percentComplete":0},{"tableIndex":0,"currentRowIndex":0,"isLast":false,"count":23781,"percentComplete":0,"tableDone":false},{"percentComplete":0,"tableDone":false,"tableIndex":0,"isLast":false,"currentRowIndex":0,"count":23881},{"isLast":false,"currentRowIndex":0,"count":23981,"percentComplete":0,"tableDone":false,"tableIndex":0},{"currentRowIndex":0,"isLast":false,"count":24081,"percentComplete":0,"tableIndex":0,"tableDone":false},{"count":24181,"tableIndex":0,"currentRowIndex":0,"isLast":false,"tableDone":false,"percentComplete":0},{"currentRowIndex":0,"tableDone":false,"isLast":false,"count":24281,"tableIndex":0,"percentComplete":0},{"isLast":false,"count":24381,"tableDone":false,"tableIndex":0,"currentRowIndex":0,"percentComplete":0},{"count":24481,"currentRowIndex":0,"tableDone":false,"tableIndex":0,"percentComplete":0,"isLast":false},{"isLast":false,"percentComplete":0,"tableDone":false,"currentRowIndex":0,"tableIndex":0,"count":24581},{"tableIndex":0,"count":24681,"tableDone":false,"currentRowIndex":0,"isLast":false,"percentComplete":0},{"isLast":false,"percentComplete":0,"count":24781,"currentRowIndex":0,"tableDone":false,"tableIndex":0},{"isLast":false,"tableDone":false,"tableIndex":0,"count":24881,"currentRowIndex":0,"percentComplete":0},{"tableDone":false,"tableIndex":0,"currentRowIndex":0,"percentComplete":0,"count":24981,"isLast":false},{"isLast":false,"count":25081,"percentComplete":0,"tableIndex":0,"tableDone":false,"currentRowIndex":0},{"percentComplete":0,"count":25181,"tableIndex":0,"currentRowIndex":0,"tableDone":false,"isLast":false},{"isLast":false,"count":25281,"currentRowIndex":0,"tableIndex":0,"percentComplete":0,"tableDone":false},{"percentComplete":0,"count":25381,"tableIndex":0,"isLast":false,"tableDone":false,"currentRowIndex":0},{"percentComplete":0,"isLast":false,"count":25481,"currentRowIndex":0,"tableDone":false,"tableIndex":0},{"isLast":false,"count":25581,"percentComplete":0,"tableIndex":0,"tableDone":false,"currentRowIndex":0},{"percentComplete":0,"currentRowIndex":0,"isLast":false,"tableIndex":0,"tableDone":false,"count":25681},{"isLast":false,"percentComplete":0,"tableDone":false,"count":25781,"tableIndex":0,"currentRowIndex":0},{"isLast":false,"tableDone":false,"count":25881,"percentComplete":0,"tableIndex":0,"currentRowIndex":0},{"currentRowIndex":0,"count":25981,"tableIndex":0,"percentComplete":0,"tableDone":true,"isLast":false}],"startTime":"2024-02-19T19:07:35Z","validationResults":{"textClassifier":{"confusionMatrix":[{"actual":"negative","expected":"negative","count":232},{"actual":"negative","count":119,"expected":"neutral"},{"expected":"positive","actual":"negative","count":29},{"actual":"neutral","expected":"negative","count":136},{"actual":"neutral","expected":"neutral","count":329},{"expected":"positive","count":82,"actual":"neutral"},{"count":25,"expected":"negative","actual":"positive"},{"actual":"positive","count":103,"expected":"neutral"},{"expected":"positive","actual":"positive","count":312}],"accuracy":0.6386247256766642,"statsByLabel":{"negative":{"precisionRecall":{"success":{"precision":0.5903307888040712,"recall":0.6105263157894737}},"count":380},"neutral":{"precisionRecall":{"success":{"precision":0.5970961887477314,"recall":0.6014625228519196}},"count":547},"positive":{"precisionRecall":{"success":{"recall":0.7090909090909091,"precision":0.7375886524822695}},"count":440}}}},"checkpointMetrics":{},"trainingResults":{"textClassifier":{"accuracy":0.924983641892152,"statsByLabel":{"neutral":{"precisionRecall":{"success":{"precision":0.924264351181862,"recall":0.9115995813112571}},"count":10509},"negative":{"count":7367,"precisionRecall":{"success":{"recall":0.9234423781729334,"precision":0.9219406423634638}}},"positive":{"precisionRecall":{"success":{"precision":0.9286147869369916,"recall":0.9437384330660087}},"count":8105}},"confusionMatrix":[{"actual":"negative","count":6803,"expected":"negative"},{"expected":"neutral","count":438,"actual":"negative"},{"actual":"negative","count":126,"expected":"positive"},{"count":467,"actual":"neutral","expected":"negative"},{"expected":"neutral","count":9580,"actual":"neutral"},{"expected":"positive","actual":"neutral","count":462},{"actual":"positive","expected":"negative","count":109},{"actual":"positive","expected":"neutral","count":347},{"expected":"positive","count":7649,"actual":"positive"}]}},"finishTime":"2024-02-19T19:07:39Z","analysedDataType":"datasource","snapshottableCheckpoints":{}},"createdDate":"2024-02-19T19:04:14Z","contentDataResult":{"createdDate":"2024-02-19T19:04:14Z"},"state":"trained","title":"Sentiment_Analisys 1","evaluationEntity":{"id":"bb627535-100d-4ea9-a0df-d91c02527336","dataResult":{},"analysedDataType":"none"},"version":"1.0","modifiedDate":"2024-02-20T18:39:11Z","settingEntity":{"taskType":"textClassifier","textClassifierLatin":"automatic","styleTransferAlgorithmType":"image","textClassifierCJKLanguage":"automatic","textClassifierCyrillicLanguage":"automatic","textClassifierScript":"latin","featureNames":[],"algorithmType":"maxEnt","handPoseClassifierAugmentations":[],"seedType":"default","augmentations":[],"iterationCount":10,"harVideoAugmentations":0,"handActionClassifierAugmentations":[]},"snapshotRole":{"withoutSnapshots":0},"validationEntity":{"analysedDataType":"auto","dataResult":{"createdDate":"2024-02-19T19:04:14Z"}},"activityEntities":["trainingStarted",[{"createdDate":"2024-02-19T19:07:35Z","subtitle":"10 iterations","title":"Training Started","event":"trainingStarted","id":"AB605969-9967-4DCA-9D98-F9C7E131B303"}],"trainingDataAdded",[{"createdDate":"2024-02-19T19:07:16Z","event":"trainingDataAdded","id":"1F5336C4-6824-42D1-A432-B3734D551630","title":"Training Data Added","subtitle":"Tweets.csv"}],"experimentCreated",[{"subtitle":"Sentiment_Analisys 1","id":"123ABE9A-A0DD-4D00-AD1A-B2EA8E23EBE1","title":"Model Source Created","event":"experimentCreated","createdDate":"2024-02-19T19:04:14Z"}],"trainingFinished",[{"event":"trainingFinished","title":"Training Completed","createdDate":"2024-02-19T19:07:39Z","id":"342E3994-CBEA-45DA-8664-9064321E4049","subtitle":"10 iterations"}]],"evaluationContainerEntity":{"validationEvaluationEntity":{"evaluationResult":{"textClassifier":{"accuracy":0.6386247256766642,"confusionMatrix":[{"actual":"negative","expected":"negative","count":232},{"count":119,"actual":"negative","expected":"neutral"},{"expected":"positive","count":29,"actual":"negative"},{"actual":"neutral","expected":"negative","count":136},{"count":329,"actual":"neutral","expected":"neutral"},{"actual":"neutral","count":82,"expected":"positive"},{"count":25,"actual":"positive","expected":"negative"},{"expected":"neutral","actual":"positive","count":103},{"count":312,"actual":"positive","expected":"positive"}],"statsByLabel":{"positive":{"count":440,"precisionRecall":{"success":{"precision":0.7375886524822695,"recall":0.7090909090909091}}},"neutral":{"count":547,"precisionRecall":{"success":{"precision":0.5970961887477314,"recall":0.6014625228519196}}},"negative":{"count":380,"precisionRecall":{"success":{"recall":0.6105263157894737,"precision":0.5903307888040712}}}}}},"id":"67a071a9-b2c1-468f-a0a6-0bc6c270d257","analysedDataType":"auto","createdDate":"2024-02-19T19:04:14Z","dataResult":{"createdDate":"2024-02-19T19:04:14Z"}},"id":"1395a215-238e-49c4-83a4-3ae1f0b152cb","previewType":"textClassifier","modifiedDate":"2024-02-20T18:39:11Z","evaluationEntities":[{"id":"42ae760b-787c-463a-9f14-4bb42e350859","createdDate":"2024-02-19T19:07:45Z","dataResult":{"createdDate":"2024-02-19T19:38:18Z"},"analysedDataType":"none"}],"createdDate":"2024-02-20T18:39:11Z","testingEvaluationEntity":{"id":"296de235-ac54-4474-a88e-6535c95c4bdc","dataResult":{"createdDate":"2024-02-19T19:04:14Z"},"analysedDataType":"none","createdDate":"2024-02-19T19:04:14Z"},"trainingEvaluationEntity":{"id":"3ff0ca4a-f49a-43a6-ab22-c76b28a092e8","analysedDataType":"none","dataResult":{"itemsCount":27348,"createdDate":"2024-02-19T19:04:14Z","dataAnalysis":{"classifierAnalysis":{"labelStats":{"neutral":11056,"negative":7747,"positive":8545}},"summary":{"classCount":3,"sampleCount":27348,"canUseValidation":1},"issues":[{"description":"3 classes found, including neutral, positive, negative","severity":"debug"},{"severity":"good","description":"27348 texts found, automatically creating validation set"},{"severity":"debug","description":"Smallest class is \"negative\" with 7747 texts"},{"severity":"debug","description":"Largest class is \"neutral\" with 11056 text"}]},"dataSourceID":"E77934DE-9744-454B-BE12-1B031104794D","dataURL":"file:\/\/\/Users\/fabiofreitas\/Documents\/datasets\/Tweets.csv","classesCount":3},"dataSourceID":"E77934DE-9744-454B-BE12-1B031104794D","evaluationResult":{"textClassifier":{"statsByLabel":{"negative":{"count":7367,"precisionRecall":{"success":{"precision":0.9219406423634638,"recall":0.9234423781729334}}},"neutral":{"precisionRecall":{"success":{"precision":0.924264351181862,"recall":0.9115995813112571}},"count":10509},"positive":{"precisionRecall":{"success":{"recall":0.9437384330660087,"precision":0.9286147869369916}},"count":8105}},"accuracy":0.924983641892152,"confusionMatrix":[{"expected":"negative","count":6803,"actual":"negative"},{"expected":"neutral","actual":"negative","count":438},{"actual":"negative","expected":"positive","count":126},{"expected":"negative","actual":"neutral","count":467},{"actual":"neutral","expected":"neutral","count":9580},{"expected":"positive","actual":"neutral","count":462},{"actual":"positive","count":109,"expected":"negative"},{"actual":"positive","count":347,"expected":"neutral"},{"actual":"positive","expected":"positive","count":7649}]}},"createdDate":"2024-02-19T19:04:14Z"}}}